{
  "features": {
    "bvc/ID-0000001": {
      "models": "UBERON:0002113",
      "comment": "Kidney - name is unused for anything, just using for human readable text"
    },
    "bvc/ID-0000003": {
      "label": "Tissue exchange system"
    },
    "bvc/ID-0000004": {
      "models": "UBERON:0001555",
      "comment": "Digestive tract"
    },
    "bvc/ID-0000006": {
      "label": "Tissue exchange system"
    },
    "bvc/ID-0000007": {
      "models": "UBERON:0001009",
      "comment": "Circulatory system"
    },
    "bvc/ID-0000009": {
      "name": "q_ac_H2O",
      "label": "Amount and potential of water in arterial circulation"
    },
    "bvc/ID-0000010": {
      "name": "q_vc_H2O_,_u_vc_osmotic",
      "label": "Amount and potential of water in venous circulation\nOsmotic pressure in venous circulation"
    },
    "bvc/ID-0000011": {
      "name": "v_lv_H2O",
      "label": "Flow of water in left ventricle"
    },
    "bvc/ID-0000012": {
      "name": "v_cc_H2O",
      "label": "Flow of water in capillary circulation"
    },
    "bvc/ID-0000017": {
      "name": "v_pt_H2O",
      "label": "Flow of water in proximal tubule of the kidney"
    },
    "bvc/ID-0000018": {
      "label": "Tissue exchange system"
    },
    "bvc/ID-0000019": {
      "name": "q_pt_H2O_,_u_pt_osmotic",
      "label": "Amount and potential of water in proximal tubule of the kidney\nOsmotic pressure in proximal tubule of the kidney"
    },
    "bvc/ID-0000021": {
      "name": "v_gl_H2O",
      "label": "Flow of water in glomeruli of the kidney"
    },
    "bvc/ID-0000023": {
      "name": "v_out2_H2O",
      "label": "Flow of water out of kidney"
    },
    "bvc/ID-0000028": {
      "name": "q_gi_H2O_,_u_gi_osmotic",
      "label": "Amount and potential of water in gastro-intestinal tract\nOsmotic pressure in gastro-intestinal tract"
    },
    "bvc/ID-0000029": {
      "name": "v_in_H2O",
      "label": "Flow of water into gastro-intestinal tract"
    },
    "bvc/ID-0000031": {
      "name": "v_gi_H2O",
      "label": "Flow of water in gastro-intestinal tract"
    },
    "bvc/ID-0000032": {
      "name": "q_gi_Na+",
      "label": "Amount and potential of sodium ions in gastro-intestinal tract"
    },
    "bvc/ID-0000033": {
      "name": "v_in_Na+",
      "label": "Flow of sodium ions into gastro-intestinal tract"
    },
    "bvc/ID-0000036": {
      "name": "v_out1_Na+",
      "label": "Flow of sodium ions out of gastro-intestinal tract"
    },
    "bvc/ID-0000038": {
      "name": "q_vc_Na+",
      "label": "Amount and potential of sodium ions in venous circulation"
    },
    "bvc/ID-0000040": {
      "name": "q_pt_Na+",
      "label": "Amount and potential of sodium ions in proximal tubule of the kidney"
    },
    "bvc/ID-0000041": {
      "name": "v_out2_Na+",
      "label": "Flow of sodium ions out of kidney"
    },
    "bvc/ID-0000043": {
      "name": "v_gl_Na+",
      "label": "Flow of sodium ions in glomeruli of the kidney"
    },
    "bvc/ID-0000050": {
      "name": "v_out1_H2O",
      "label": "Flow of water out of gastro-intestinal tract"
    },
    "bvc/ID-0000053": {
      "name": "q_gi.epi_Na+",
      "label": "Amount and potential of sodium ions in epithelial cell of gastro-intestinal tract"
    },
    "bvc/ID-0000059": {
      "name": "q_pt.epi_Na+",
      "label": "Amount and potential of sodium ions in epithelial cell of proximal tubule of the kidney"
    },
    "bvc/ID-0000064": {
      "name": "v_gi_Na+",
      "label": "Flow of sodium ions in epithelial cell of gastro-intestinal tract"
    },
    "bvc/ID-0000065": {
      "name": "v_giEpi_NKE",
      "label": "Flow of sodium ions through NKE ATPase in epithelial cell of gastro-intestinal tract"
    },
    "bvc/ID-0000066": {
      "name": "v_pt_Na+",
      "label": "Flow of sodium ions in epithelial cell of proximal tubule of the kidney"
    },
    "bvc/ID-0000067": {
      "name": "v_ptEpi_NKE",
      "label": "Flow of sodium ions through NKE ATPase in epithelial cell of proximal tubule of the kidney"
    }
  }
}
